ExtractOSM/calc_latlon.py
ExtractOSM/classification_schema.py
ExtractOSM/compare_rankings.py
ExtractOSM/elevation_fuzzy_match.py
ExtractOSM/enrich_features.py
ExtractOSM/enrichment_manager.py
ExtractOSM/extract_health_ratings.py
ExtractOSM/extract_osm.py
ExtractOSM/generate_area_score.py
ExtractOSM/geo_fuzzy_match.py
ExtractOSM/normalize_units.py
ExtractOSM/osm_data.py
ExtractOSM/osm_handler.py
ExtractOSM/piecewise_score.py
ExtractOSM/poi_richness.py
ExtractOSM/publish_osm.py
ExtractOSM/run_extract_osm.py
ExtractOSM/significant_tag_counter.py
ExtractOSM/text_similarity.py
ExtractOSM/text_substitution.py
ExtractOSM/wikipedia_props.py
ExtractOSM/yaml_config.py
extractosm-1.3.2.dist-info/licenses/LICENSE
extractosm-1.3.2.dist-info/METADATA
extractosm-1.3.2.dist-info/WHEEL
extractosm-1.3.2.dist-info/entry_points.txt
extractosm-1.3.2.dist-info/top_level.txt
extractosm-1.3.2.dist-info/RECORD
