Metadata-Version: 2.4
Name: ExtractOSM
Version: 1.3.2
Summary: Extract nodes from an OSM file
Author: corb
Project-URL: Repository, https://github.com/corb555/ExtractOSM
Keywords: OSM,GIS
Classifier: Intended Audience :: End Users/Desktop
Classifier: Topic :: Scientific/Engineering :: GIS
Classifier: License :: OSI Approved :: MIT License
Classifier: Programming Language :: Python
Classifier: Programming Language :: Python :: 3.9
Requires-Python: >=3.9
License-File: LICENSE
Dynamic: license-file
